webcam/__init__.py
webcam/frontend/build/asset-manifest.json
webcam/frontend/build/bootstrap.min.css
webcam/frontend/build/index.html
webcam/frontend/build/precache-manifest.6fa19f6c740c2a8bee0cfce4e5534e19.js
webcam/frontend/build/service-worker.js
webcam/frontend/build/static/js/2.b5a65889.chunk.js
webcam/frontend/build/static/js/2.b5a65889.chunk.js.LICENSE.txt
webcam/frontend/build/static/js/2.b5a65889.chunk.js.map
webcam/frontend/build/static/js/main.28042bf7.chunk.js
webcam/frontend/build/static/js/main.28042bf7.chunk.js.map
webcam/frontend/build/static/js/runtime-main.afc2dea7.js
webcam/frontend/build/static/js/runtime-main.afc2dea7.js.map
streamlit_webcam_example-0.1.0.dist-info/LICENSE
streamlit_webcam_example-0.1.0.dist-info/METADATA
streamlit_webcam_example-0.1.0.dist-info/WHEEL
streamlit_webcam_example-0.1.0.dist-info/top_level.txt
streamlit_webcam_example-0.1.0.dist-info/RECORD
