Metadata-Version: 2.1
Name: streamlit-webcam-example
Version: 0.1.0
Summary: UNKNOWN
Home-page: UNKNOWN
Author: Tim Conkling
Author-email: tim@streamlit.io
License: UNKNOWN
Platform: UNKNOWN
Requires-Python: >=3.7
Requires-Dist: streamlit (>=0.73)
